{
  "type": "Prerender",
  "expiration": false,
  "group": 1,
  "bypassToken": "e9ef17506b4a1a023c82233733bb6245",
  "experimentalBypassFor": [
    {
      "type": "header",
      "key": "Next-Action"
    },
    {
      "type": "header",
      "key": "content-type",
      "value": "multipart/form-data;.*"
    }
  ],
  "fallback": {
    "type": "FileFsRef",
    "mode": 33188,
    "contentType": "image/svg+xml",
    "fsPath": "icon.svg.prerender-fallback.body"
  },
  "initialHeaders": {
    "cache-control": "public, immutable, no-transform, max-age=31536000",
    "content-type": "image/svg+xml",
    "x-next-cache-tags": "_N_T_/layout,_N_T_/icon.svg/layout,_N_T_/icon.svg/route,_N_T_/icon.svg",
    "vary": "RSC, Next-Router-State-Tree, Next-Router-Prefetch, Next-Router-Segment-Prefetch"
  },
  "allowQuery": [],
  "allowHeader": [
    "host",
    "x-matched-path",
    "x-prerender-revalidate",
    "x-prerender-revalidate-if-generated",
    "x-next-revalidated-tags",
    "x-next-revalidate-tag-token"
  ]
}
